pyef/.DS_Store
pyef/__init__.py
pyef/__main__.py
pyef/_config.py
pyef/cli.py
pyef/data/.DS_Store
pyef/data/bigdeal2022/final_match/final_match.csv
pyef/data/bigdeal2022/qualifying_match/Qualifying Math Data.xlsx
pyef/data/bigdeal2022/qualifying_match/data_round_1.csv
pyef/data/gefcom2012/.DS_Store
pyef/data/gefcom2012/load/Holiday_List.csv
pyef/data/gefcom2012/load/Load_benchmark.csv
pyef/data/gefcom2012/load/Load_history.csv
pyef/data/gefcom2012/load/Load_solution.csv
pyef/data/gefcom2012/load/temperature_history.csv
pyef/data/gefcom2012/load/temperature_solution.csv
pyef/data/gefcom2012/wind/Read Me First.txt
pyef/data/gefcom2012/wind/benchmark.csv
pyef/data/gefcom2012/wind/test.csv
pyef/data/gefcom2012/wind/train.csv
pyef/data/gefcom2012/wind/windforecasts_wf1.csv
pyef/data/gefcom2012/wind/windforecasts_wf2.csv
pyef/data/gefcom2012/wind/windforecasts_wf3.csv
pyef/data/gefcom2012/wind/windforecasts_wf4.csv
pyef/data/gefcom2012/wind/windforecasts_wf5.csv
pyef/data/gefcom2012/wind/windforecasts_wf6.csv
pyef/data/gefcom2012/wind/windforecasts_wf7.csv
pyef/data/gefcom2012/wind/windpowermeasurements.csv
pyef/datasets.py
pyef/evaluator.py
pyef/forecaster.py
pyef/logger.py
pyef/py.typed
pyef/timeframes.py
pyef-0.1.0.dist-info/entry_points.txt
pyef-0.1.0.dist-info/WHEEL
pyef-0.1.0.dist-info/METADATA
pyef-0.1.0.dist-info/licenses/LICENSE
pyef-0.1.0.dist-info/RECORD
