Metadata-Version: 2.1
Name: pyef
Version: 0.1.0
Summary: Energy Forecasting Toolkit in Python
License: MIT
Author-email: Bhav Sardana <sardana.bhav@gmail.com>
Requires-Python: >=3.8
Classifier: Development Status :: 4 - Beta
Classifier: Intended Audience :: Developers
Classifier: Programming Language :: Python
Classifier: Programming Language :: Python :: 3
Classifier: Programming Language :: Python :: 3 :: Only
Classifier: Programming Language :: Python :: 3.10
Classifier: Programming Language :: Python :: 3.11
Classifier: Programming Language :: Python :: 3.7
Classifier: Programming Language :: Python :: 3.8
Classifier: Programming Language :: Python :: 3.9
Classifier: Topic :: Documentation
Classifier: Topic :: Software Development
Classifier: Topic :: Software Development :: Documentation
Classifier: Topic :: Utilities
Classifier: Typing :: Typed
Requires-Dist: memo>=0.2.3
Requires-Dist: numpy==1.24.0
Requires-Dist: optioneer>=1.0.3
Requires-Dist: pandas>=1.5.2
Requires-Dist: patsy>=0.5.3
Requires-Dist: rich>=12.6.0
Requires-Dist: scikit-learn>=1.2.0
Provides-Extra: plot
Requires-Dist: plotly>=5.11.0; extra == "plot"
Requires-Dist: matplotlib>=3.6.2; extra == "plot"
Project-URL: Changelog, https://sardanabhav.github.io/pyef/changelog
Project-URL: Discussions, https://github.com/sardanabhav/pyef/discussions
Project-URL: Documentation, https://sardanabhav.github.io/pyef
Project-URL: Funding, https://github.com/sponsors/sardanabhav
Project-URL: Gitter, https://gitter.im/pyef/community
Project-URL: Homepage, https://sardanabhav.github.io/pyef
Project-URL: Issues, https://github.com/sardanabhav/pyef/issues
Project-URL: Repository, https://github.com/sardanabhav/pyef
